pysisyphus/Geometry.py
pysisyphus/MOCoeffs.py
pysisyphus/TablePrinter.py
pysisyphus/__init__.py
pysisyphus/color.py
pysisyphus/config.py
pysisyphus/constants.py
pysisyphus/elem_data.py
pysisyphus/exceptions.py
pysisyphus/executors.py
pysisyphus/filtertrj.py
pysisyphus/finite_diffs.py
pysisyphus/helpers.py
pysisyphus/helpers_pure.py
pysisyphus/hessian_proj.py
pysisyphus/init_logging.py
pysisyphus/linalg.py
pysisyphus/linalg_affine3.py
pysisyphus/pack.py
pysisyphus/peakdetect.py
pysisyphus/plot.py
pysisyphus/plot_ascii.py
pysisyphus/plot_helpers.py
pysisyphus/run.py
pysisyphus/socket_helper.py
pysisyphus/testing.py
pysisyphus/thermo.py
pysisyphus/timing.py
pysisyphus/trj.py
pysisyphus/typing.py
pysisyphus/version.py
pysisyphus/xyzloader.py
pysisyphus/yaml_mods.py
pysisyphus/basis_library/def2-universal-jfit.json
pysisyphus/basis_library/minao.json
pysisyphus/basis_library/parse_minao.py
pysisyphus/benchmarks/Benchmark.py
pysisyphus/benchmarks/__init__.py
pysisyphus/benchmarks/data.py
pysisyphus/calculators/AFIR.py
pysisyphus/calculators/AnaPot.py
pysisyphus/calculators/AnaPot2.py
pysisyphus/calculators/AnaPot3.py
pysisyphus/calculators/AnaPot4.py
pysisyphus/calculators/AnaPotBase.py
pysisyphus/calculators/AnaPotCBM.py
pysisyphus/calculators/AtomAtomTransTorque.py
pysisyphus/calculators/CFOUR.py
pysisyphus/calculators/Calculator.py
pysisyphus/calculators/CerjanMiller.py
pysisyphus/calculators/Composite.py
pysisyphus/calculators/ConicalIntersection.py
pysisyphus/calculators/DFTBp.py
pysisyphus/calculators/DFTD3.py
pysisyphus/calculators/DFTD4.py
pysisyphus/calculators/Dalton.py
pysisyphus/calculators/Dimer.py
pysisyphus/calculators/Dummy.py
pysisyphus/calculators/EGO.py
pysisyphus/calculators/EnergyMin.py
pysisyphus/calculators/ExternalPotential.py
pysisyphus/calculators/FakeASE.py
pysisyphus/calculators/FourWellAnaPot.py
pysisyphus/calculators/FreeEndNEBPot.py
pysisyphus/calculators/Gaussian09.py
pysisyphus/calculators/Gaussian16.py
pysisyphus-1.0.0.dist-info/licenses/LICENSE
pysisyphus-1.0.0.dist-info/METADATA
pysisyphus-1.0.0.dist-info/WHEEL
pysisyphus-1.0.0.dist-info/entry_points.txt
pysisyphus-1.0.0.dist-info/top_level.txt
pysisyphus-1.0.0.dist-info/RECORD
