Metadata-Version: 2.4
Name: pysisyphus
Version: 1.0.0
Summary: Python suite for exploring potential energy surfaces.
Home-page: https://github.com/eljost/pysisyphus
Maintainer: Johannes Steinmetzer
Maintainer-email: johannes.steinmetzer@uni-jena.de
License: GNU General Public License v3 (GPLv3)
Platform: unix
Classifier: License :: OSI Approved :: GNU General Public License v3 (GPLv3)
Requires-Python: >=3.9
License-File: LICENSE
Requires-Dist: autograd
Requires-Dist: dask
Requires-Dist: distributed
Requires-Dist: h5py
Requires-Dist: fabric
Requires-Dist: jax
Requires-Dist: jinja2
Requires-Dist: matplotlib
Requires-Dist: natsort
Requires-Dist: numba
Requires-Dist: numpy
Requires-Dist: networkx
Requires-Dist: optuna
Requires-Dist: pandas
Requires-Dist: psutil
Requires-Dist: pyyaml
Requires-Dist: rmsd
Requires-Dist: scipy
Requires-Dist: sympy
Requires-Dist: scikit-learn
Provides-Extra: test
Requires-Dist: pyscf; extra == "test"
Requires-Dist: pytest; extra == "test"
Requires-Dist: pytest-cov; extra == "test"
Requires-Dist: ase>=3.23.0; extra == "test"
Requires-Dist: qcengine; extra == "test"
Provides-Extra: full
Requires-Dist: pyscf; extra == "full"
Requires-Dist: pytest; extra == "full"
Requires-Dist: pytest-cov; extra == "full"
Requires-Dist: ase>=3.23.0; extra == "full"
Requires-Dist: qcengine; extra == "full"
Requires-Dist: ursina; extra == "full"
Requires-Dist: trexio; extra == "full"
Provides-Extra: doc
Requires-Dist: sphinx<=8.2.0; extra == "doc"
Requires-Dist: sphinx-rtd-theme; extra == "doc"
Requires-Dist: sphinx_autodoc_typehints; extra == "doc"
Dynamic: license-file
